.gitignore
MANIFEST.in
README.rst
bootstrap.py
buildout.cfg
plone.cfg
setup.cfg
setup.py
collective/__init__.py
collective.object.egg-info/PKG-INFO
collective.object.egg-info/SOURCES.txt
collective.object.egg-info/dependency_links.txt
collective.object.egg-info/entry_points.txt
collective.object.egg-info/namespace_packages.txt
collective.object.egg-info/not-zip-safe
collective.object.egg-info/paster_plugins.txt
collective.object.egg-info/requires.txt
collective.object.egg-info/top_level.txt
collective/object/__init__.py
collective/object/configure.zcml
collective/object/object.py
collective/object/tests.py
collective/object/locales/README.txt
collective/object/locales/en/LC_MESSAGES/collective.object.mo
collective/object/locales/en/LC_MESSAGES/collective.object.po
collective/object/locales/nl/LC_MESSAGES/collective.object.mo
collective/object/locales/nl/LC_MESSAGES/collective.object.po
collective/object/object_templates/add.pt
collective/object/object_templates/edit.pt
collective/object/object_templates/view.pt
collective/object/profiles/default/metadata.xml
collective/object/profiles/default/types.xml
collective/object/profiles/default/types/Object.xml
collective/object/resources/README.txt
docs/HISTORY.rst
docs/INSTALL.txt
docs/LICENSE.GPL
docs/LICENSE.txt