Metadata-Version: 1.1
Name: collective.object
Version: 0.6
Summary: Information about an object typically collected by museums
Home-page: https://github.com/collective/collective.object
Author: Andre Gonclaves
Author-email: andre@intk.com
License: GPL
Keywords: Plone
Platform: UNKNOWN
Classifier: Framework :: Plone
Classifier: Programming Language :: Python
Classifier: Topic :: Software Development :: Libraries :: Python Modules
